cmip_ref/__init__.py
cmip_ref/_config_helpers.py
cmip_ref/alembic.ini
cmip_ref/config.py
cmip_ref/constants.py
cmip_ref/database.py
cmip_ref/provider_registry.py
cmip_ref/py.typed
cmip_ref/solver.py
cmip_ref/testing.py
cmip_ref/cli/__init__.py
cmip_ref/cli/_utils.py
cmip_ref/cli/config.py
cmip_ref/cli/datasets.py
cmip_ref/cli/executions.py
cmip_ref/cli/providers.py
cmip_ref/cli/solve.py
cmip_ref/dataset_registry/obs4ref_reference.txt
cmip_ref/dataset_registry/sample_data.txt
cmip_ref/datasets/__init__.py
cmip_ref/datasets/base.py
cmip_ref/datasets/cmip6.py
cmip_ref/datasets/obs4mips.py
cmip_ref/datasets/pmp_climatology.py
cmip_ref/datasets/utils.py
cmip_ref/executor/__init__.py
cmip_ref/executor/local.py
cmip_ref/migrations/README
cmip_ref/migrations/env.py
cmip_ref/migrations/script.py.mako
cmip_ref/migrations/versions/2024-11-24T2134_ea2aa1134cb3_dataset_rework.py
cmip_ref/migrations/versions/2024-12-05T2210_4b95a617184e_add_metrics.py
cmip_ref/migrations/versions/2024-12-19T1216_4a447fbf6d65_metric_add_output_fragment.py
cmip_ref/migrations/versions/2025-02-10T0935_c1818a18d87f_remove_result_constraint.py
cmip_ref/migrations/versions/2025-03-03T0844_6634396f139a_adding_obs4mips.py
cmip_ref/migrations/versions/2025-03-07T0518_1f5969a92b85_result_output.py
cmip_ref/migrations/versions/2025-03-12T1141_c5de99c14533_refactor_execution_to_execution_group.py
cmip_ref/migrations/versions/2025-04-14T1109_e1cdda7dcf1d_result_fix_pk.py
cmip_ref/migrations/versions/2025-04-14T1549_904f2f2db24a_metric_values.py
cmip_ref/migrations/versions/2025-04-14T1609_6bc6ad5fc5e1_execution_selectors.py
cmip_ref/migrations/versions/2025-04-14T2137_4fc26a7d2d28_cmip6_mark_nullable.py
cmip_ref/migrations/versions/2025-04-16T1606_4ac252ba38ed_pmp-climatologies.py
cmip_ref/models/__init__.py
cmip_ref/models/base.py
cmip_ref/models/dataset.py
cmip_ref/models/metric.py
cmip_ref/models/metric_execution.py
cmip_ref/models/metric_value.py
cmip_ref/models/provider.py
cmip_ref-0.4.1.dist-info/METADATA
cmip_ref-0.4.1.dist-info/WHEEL
cmip_ref-0.4.1.dist-info/entry_points.txt
cmip_ref-0.4.1.dist-info/licenses/LICENCE
cmip_ref-0.4.1.dist-info/licenses/NOTICE
cmip_ref-0.4.1.dist-info/RECORD
